AuthMiddleware/__init__.py
AuthMiddleware/middleware.py
django_authmiddleware-0.0.4.dist-info/LICENSE
django_authmiddleware-0.0.4.dist-info/METADATA
django_authmiddleware-0.0.4.dist-info/WHEEL
django_authmiddleware-0.0.4.dist-info/top_level.txt
django_authmiddleware-0.0.4.dist-info/RECORD
