Metadata-Version: 2.1
Name: django-authmiddleware
Version: 0.0.4
Summary: Django middleware to enforce login before accessing certain URL's
Home-page: https://github.com/AvishrantsSh/AuthRequiredMiddleware
Author: AvishrantSh (Avishrant Sharma)
Author-email: <avishrants@gmail.com>
License: UNKNOWN
Project-URL: Bug Tracker, https://github.com/AvishrantsSh/AuthRequiredMiddleware/issues
Platform: UNKNOWN
Classifier: Programming Language :: Python :: 3
Classifier: License :: OSI Approved :: MIT License
Requires-Python: >=3.6
License-File: LICENSE
